odoo/addons/stock_picking_restrict_cancel_with_orig_move/README.rst
odoo/addons/stock_picking_restrict_cancel_with_orig_move/__init__.py
odoo/addons/stock_picking_restrict_cancel_with_orig_move/__manifest__.py
odoo/addons/stock_picking_restrict_cancel_with_orig_move/i18n/stock_picking_restrict_cancel_with_orig_move.pot
odoo/addons/stock_picking_restrict_cancel_with_orig_move/models/__init__.py
odoo/addons/stock_picking_restrict_cancel_with_orig_move/models/stock_move.py
odoo/addons/stock_picking_restrict_cancel_with_orig_move/tests/__init__.py
odoo/addons/stock_picking_restrict_cancel_with_orig_move/tests/test_restrict_cancel.py
odoo11_addon_stock_picking_restrict_cancel_with_orig_move-11.0.1.0.2.dist-info/DESCRIPTION.rst
odoo11_addon_stock_picking_restrict_cancel_with_orig_move-11.0.1.0.2.dist-info/METADATA
odoo11_addon_stock_picking_restrict_cancel_with_orig_move-11.0.1.0.2.dist-info/RECORD
odoo11_addon_stock_picking_restrict_cancel_with_orig_move-11.0.1.0.2.dist-info/WHEEL
odoo11_addon_stock_picking_restrict_cancel_with_orig_move-11.0.1.0.2.dist-info/metadata.json
odoo11_addon_stock_picking_restrict_cancel_with_orig_move-11.0.1.0.2.dist-info/top_level.txt
